pycycle/__init__.py
pycycle/__version__.py
pycycle/cli.py
pycycle/utils.py
pycycle-0.0.8.dist-info/DESCRIPTION.rst
pycycle-0.0.8.dist-info/METADATA
pycycle-0.0.8.dist-info/RECORD
pycycle-0.0.8.dist-info/WHEEL
pycycle-0.0.8.dist-info/entry_points.txt
pycycle-0.0.8.dist-info/metadata.json
pycycle-0.0.8.dist-info/top_level.txt
