Metadata-Version: 2.0
Name: pycycle
Version: 0.0.8
Summary: Find and repair your import cycles in any project
Home-page: https://github.com/bndr/pycycle
Author: Vadim Kravcenko
Author-email: vadim.kravcenko@gmail.com
License: MIT
Platform: UNKNOWN
Classifier: Programming Language :: Python
Classifier: Programming Language :: Python :: 2.6
Classifier: Programming Language :: Python :: 2.7
Classifier: Programming Language :: Python :: 3
Classifier: Programming Language :: Python :: 3.3
Classifier: Programming Language :: Python :: 3.4
Classifier: Programming Language :: Python :: 3.5
Classifier: Programming Language :: Python :: 3.6
Classifier: Programming Language :: Python :: Implementation :: CPython
Classifier: Programming Language :: Python :: Implementation :: PyPy
Requires-Dist: click (>=6.7)
Requires-Dist: click-completion
Requires-Dist: crayons
Requires-Dist: pytest
